{
  "generator-jhipster": {
    "promptValues": {
      "packageName": "com.maximeandre.jhipstertest",
      "nativeLanguage": "en"
    },
    "jhipsterVersion": "6.10.1",
    "applicationType": "monolith",
    "baseName": "jhipstertest",
    "packageName": "com.maximeandre.jhipstertest",
    "packageFolder": "com/maximeandre/jhipstertest",
    "serverPort": "8080",
    "authenticationType": "jwt",
    "cacheProvider": "hazelcast",
    "enableHibernateCache": false,
    "websocket": false,
    "databaseType": "mongodb",
    "devDatabaseType": "mongodb",
    "prodDatabaseType": "mongodb",
    "searchEngine": false,
    "messageBroker": false,
    "serviceDiscoveryType": false,
    "buildTool": "maven",
    "enableSwaggerCodegen": false,
    "jwtSecretKey": "NjhmOTcyNjIzNWZhYTBjOTZlMmE3YjllYTI5NmNlOGVkYjI1MWRjNDAyZmExNzNkNTI2NDU3MjA4M2JkZGNiY2Y0NzkxN2FlNTU1ZTM5MDgwMGFlOTJmMTQ5Mjc2YjBmZmViMzI4ZDdiNmIyNzM4ZWY2Y2I0ZDFhY2IxN2M4ZGM=",
    "embeddableLaunchScript": false,
    "useSass": true,
    "clientPackageManager": "npm",
    "clientFramework": "angularX",
    "clientTheme": "none",
    "clientThemeVariant": "",
    "creationTimestamp": 1600513601169,
    "testFrameworks": ["protractor"],
    "jhiPrefix": "jhi",
    "entitySuffix": "",
    "dtoSuffix": "DTO",
    "otherModules": [],
    "enableTranslation": true,
    "nativeLanguage": "en",
    "languages": ["en", "fr"],
    "blueprints": []
  }
}
